cosmap/__init__.py
cosmap/analysis/__init__.py
cosmap/analysis/analysis.py
cosmap/analysis/base_analysis.json
cosmap/analysis/dependencies.py
cosmap/analysis/errors.py
cosmap/analysis/files.json
cosmap/analysis/manage.py
cosmap/analysis/plugins.py
cosmap/analysis/sampler.py
cosmap/analysis/setup.py
cosmap/analysis/task.py
cosmap/analysis/transformation.py
cosmap/analysis/utils.py
cosmap/api/cmds.py
cosmap/config/__init__.py
cosmap/config/analysis.py
cosmap/config/block.py
cosmap/config/model.py
cosmap/config/models/__init__.py
cosmap/config/models/geometry.py
cosmap/config/models/sky.py
cosmap/config/models/test.py
cosmap/config/utils.py
cosmap/dataset/__init__.py
cosmap/dataset/plugins.py
cosmap/entrypoint.py
cosmap/locations.py
cosmap/output/__init__.py
cosmap/output/output.py
cosmap/output/parser.py
cosmap/output/writer.py
cosmap/plugins/__init__.py
cosmap/plugins/manage.py
cosmap/plugins/plugins.json
cosmap/plugins/register.py
cosmap-0.3.2.dist-info/METADATA
cosmap-0.3.2.dist-info/WHEEL
cosmap-0.3.2.dist-info/entry_points.txt
cosmap-0.3.2.dist-info/RECORD
