Metadata-Version: 2.3
Name: cosmap
Version: 0.3.2
Summary: 
Author: Patrick Wells
Author-email: patrick@astropatty.com
Requires-Python: >=3.11
Classifier: Programming Language :: Python :: 3
Classifier: Programming Language :: Python :: 3.11
Classifier: Programming Language :: Python :: 3.12
Classifier: Programming Language :: Python :: 3.13
Requires-Dist: astropy (>=7.0.1,<8.0.0)
Requires-Dist: click (>=8.1.3)
Requires-Dist: dask[distributed] (>=2023.4.0)
Requires-Dist: heinlein (>=0.10.8,<0.11.0)
Requires-Dist: loguru (>=0.7.0)
Requires-Dist: networkx (>=3.1)
Requires-Dist: pluggy (>=1.2.0)
Requires-Dist: pydantic (>=2.0.0)
Requires-Dist: toml (>=0.10.2)
